frequenz/microgrid/betterproto/__init__.py
frequenz/microgrid/betterproto/py.typed
frequenz/microgrid/betterproto/frequenz/__init__.py
frequenz/microgrid/betterproto/frequenz/api/__init__.py
frequenz/microgrid/betterproto/frequenz/api/common/__init__.py
frequenz/microgrid/betterproto/frequenz/api/common/v1/__init__.py
frequenz/microgrid/betterproto/frequenz/api/common/v1/grid/__init__.py
frequenz/microgrid/betterproto/frequenz/api/common/v1/metrics/__init__.py
frequenz/microgrid/betterproto/frequenz/api/common/v1/microgrid/__init__.py
frequenz/microgrid/betterproto/frequenz/api/common/v1/microgrid/components/__init__.py
frequenz/microgrid/betterproto/frequenz/api/common/v1/microgrid/sensors/__init__.py
frequenz/microgrid/betterproto/frequenz/api/microgrid/__init__.py
frequenz/microgrid/betterproto/frequenz/api/microgrid/v1/__init__.py
frequenz/microgrid/betterproto/google/__init__.py
frequenz/microgrid/betterproto/google/api/__init__.py
frequenz_microgrid_betterproto-0.17.0.2.dist-info/LICENSE
frequenz_microgrid_betterproto-0.17.0.2.dist-info/METADATA
frequenz_microgrid_betterproto-0.17.0.2.dist-info/WHEEL
frequenz_microgrid_betterproto-0.17.0.2.dist-info/top_level.txt
frequenz_microgrid_betterproto-0.17.0.2.dist-info/RECORD
