Metadata-Version: 2.1
Name: frequenz-microgrid-betterproto
Version: 0.17.0.2
Summary: Bindings to the microgrid API generated using betterproto
Author-email: Frequenz Energy-as-a-Service GmbH <floss@frequenz.com>
License: MIT
Project-URL: Documentation, https://frequenz-floss.github.io/frequenz-microgrid-betterproto-python/
Project-URL: Changelog, https://github.com/frequenz-floss/frequenz-microgrid-betterproto-python/releases
Project-URL: Issues, https://github.com/frequenz-floss/frequenz-microgrid-betterproto-python/issues
Project-URL: Repository, https://github.com/frequenz-floss/frequenz-microgrid-betterproto-python
Project-URL: Support, https://github.com/frequenz-floss/frequenz-microgrid-betterproto-python/discussions/categories/support
Keywords: api,betterproto,bindings,frequenz,grpc,lib,library,microgrid,proto,protobuf,python,rpc
Classifier: Development Status :: 3 - Alpha
Classifier: Intended Audience :: Developers
Classifier: License :: OSI Approved :: MIT License
Classifier: Programming Language :: Python :: 3
Classifier: Programming Language :: Python :: 3 :: Only
Classifier: Topic :: Software Development :: Libraries
Classifier: Typing :: Typed
Requires-Python: <4,>=3.11
License-File: LICENSE
Requires-Dist: betterproto ==2.0.0b6
Requires-Dist: typing-extensions <5,>=4.5.0
Provides-Extra: dev
Requires-Dist: frequenz-microgrid-betterproto[dev-flake8,dev-formatting,dev-mkdocs,dev-mypy,dev-noxfile,dev-pylint,dev-pytest] ; extra == 'dev'
Provides-Extra: dev-flake8
Requires-Dist: flake8 ==7.0.0 ; extra == 'dev-flake8'
Requires-Dist: flake8-docstrings ==1.7.0 ; extra == 'dev-flake8'
Requires-Dist: flake8-pyproject ==1.2.3 ; extra == 'dev-flake8'
Requires-Dist: pydoclint ==0.4.1 ; extra == 'dev-flake8'
Requires-Dist: pydocstyle ==6.3.0 ; extra == 'dev-flake8'
Provides-Extra: dev-formatting
Requires-Dist: black ==24.4.2 ; extra == 'dev-formatting'
Requires-Dist: isort ==5.13.2 ; extra == 'dev-formatting'
Provides-Extra: dev-mkdocs
Requires-Dist: black ==24.4.2 ; extra == 'dev-mkdocs'
Requires-Dist: Markdown ==3.6 ; extra == 'dev-mkdocs'
Requires-Dist: mike ==2.1.1 ; extra == 'dev-mkdocs'
Requires-Dist: mkdocs-gen-files ==0.5.0 ; extra == 'dev-mkdocs'
Requires-Dist: mkdocs-literate-nav ==0.6.1 ; extra == 'dev-mkdocs'
Requires-Dist: mkdocs-macros-plugin ==1.0.5 ; extra == 'dev-mkdocs'
Requires-Dist: mkdocs-material ==9.5.24 ; extra == 'dev-mkdocs'
Requires-Dist: mkdocstrings[python] ==0.25.1 ; extra == 'dev-mkdocs'
Requires-Dist: mkdocstrings-python ==1.10.3 ; extra == 'dev-mkdocs'
Requires-Dist: frequenz-repo-config[lib] ==0.9.2 ; extra == 'dev-mkdocs'
Provides-Extra: dev-mypy
Requires-Dist: mypy ==1.10.0 ; extra == 'dev-mypy'
Requires-Dist: types-Markdown ==3.6.0.20240316 ; extra == 'dev-mypy'
Requires-Dist: frequenz-microgrid-betterproto[dev-mkdocs,dev-noxfile,dev-pytest] ; extra == 'dev-mypy'
Provides-Extra: dev-noxfile
Requires-Dist: nox ==2024.4.15 ; extra == 'dev-noxfile'
Requires-Dist: frequenz-repo-config[lib] ==0.9.2 ; extra == 'dev-noxfile'
Provides-Extra: dev-pylint
Requires-Dist: pylint ==3.2.2 ; extra == 'dev-pylint'
Requires-Dist: frequenz-microgrid-betterproto[dev-mkdocs,dev-noxfile,dev-pytest] ; extra == 'dev-pylint'
Provides-Extra: dev-pytest
Requires-Dist: pytest ==8.2.1 ; extra == 'dev-pytest'
Requires-Dist: frequenz-repo-config[extra-lint-examples] ==0.9.2 ; extra == 'dev-pytest'
Requires-Dist: pytest-mock ==3.14.0 ; extra == 'dev-pytest'
Requires-Dist: pytest-asyncio ==0.23.7 ; extra == 'dev-pytest'
